impaper-0.1.5.dist-info/METADATA
impaper-0.1.5.dist-info/WHEEL
impaper/__init__.py
impaper/canvas.py
impaper/charwidth.py
impaper/config.py
impaper/draw.py
impaper/res/sarasa-mono-sc-regular.ttf
impaper/typesetting.py
impaper-0.1.5.dist-info/RECORD
