Metadata-Version: 2.1
Name: impaper
Version: 0.1.5
Summary: 通过文本生成图片，会自动计算折行，默认使用自带的等距更纱黑体（简体中文）字体
Author-Email: zombie110year <zombie110year@outlook.com>
License: MIT
Classifier: Programming Language :: Python :: 3
Classifier: License :: OSI Approved :: MIT License
Classifier: Topic :: Text Processing
Project-URL: Repository, https://github.com/zombie110year/impaper
Requires-Python: <4.0,>=3.10
Requires-Dist: pillow>=9.0.0
Requires-Dist: pydantic>=1.0.0
